{
  "sailnumber": "POL/GER798",
  "country": "POL",
  "name": "HAPPY-X",
  "rating": {
    "gph": 652.4,
    "osn": 636.6,
    "triple_offshore": [
      0.8173,
      1.0332,
      1.1355
    ],
    "triple_inshore": [
      0.6347,
      0.8355,
      0.94
    ]
  },
  "boat": {
    "builder": "X-YACHTS",
    "type": "X-332",
    "designer": "JEPPESEN",
    "year": 1994,
    "sizes": {
      "loa": 10.06,
      "beam": 3.28,
      "draft": 1.83,
      "displacement": 4636.0,
      "genoa": 30.82,
      "main": 35.3,
      "spinnaker": 61.78,
      "spinnaker_asym": 66.18,
      "crew": 270.0,
      "wetted_surface": 23.73
    },
    "stability_index": -1.0
  },
  "vpp": {
    "angles": [
      52,
      60,
      75,
      90,
      110,
      120,
      135,
      150
    ],
    "speeds": [
      4,
      6,
      8,
      10,
      12,
      14,
      16,
      20,
      24
    ],
    "52": [
      3.86,
      5.17,
      6.06,
      6.52,
      6.69,
      6.76,
      6.81,
      6.84,
      6.75
    ],
    "60": [
      4.1,
      5.44,
      6.3,
      6.74,
      6.92,
      7.0,
      7.05,
      7.1,
      7.05
    ],
    "75": [
      4.29,
      5.63,
      6.47,
      6.92,
      7.16,
      7.3,
      7.38,
      7.51,
      7.54
    ],
    "90": [
      4.15,
      5.54,
      6.49,
      7.01,
      7.25,
      7.49,
      7.67,
      7.91,
      8.04
    ],
    "110": [
      4.08,
      5.54,
      6.59,
      7.16,
      7.56,
      7.9,
      8.13,
      8.49,
      8.59
    ],
    "120": [
      3.92,
      5.37,
      6.44,
      7.06,
      7.5,
      7.9,
      8.29,
      8.92,
      9.37
    ],
    "135": [
      3.42,
      4.79,
      5.91,
      6.71,
      7.2,
      7.62,
      8.05,
      8.96,
      10.34
    ],
    "150": [
      2.81,
      4.03,
      5.11,
      6.02,
      6.7,
      7.14,
      7.52,
      8.31,
      9.27
    ],
    "beat_angle": [
      43,
      43,
      41.1,
      40.1,
      39.8,
      39.8,
      39.9,
      40.7,
      42.7
    ],
    "beat_vmg": [
      2.49,
      3.41,
      4.09,
      4.47,
      4.61,
      4.67,
      4.7,
      4.67,
      4.48
    ],
    "run_angle": [
      143.1,
      143.1,
      147.6,
      149.5,
      160.3,
      166.8,
      178.1,
      178.6,
      178.1
    ],
    "run_vmg": [
      2.43,
      3.49,
      4.42,
      5.21,
      5.88,
      6.48,
      6.98,
      7.72,
      8.48
    ]
  }
}