{
  "sailnumber": "ECU/ECU10000",
  "country": "ECU",
  "name": "READY-SET-GO",
  "rating": {
    "gph": 511.5,
    "osn": 498.3,
    "triple_offshore": [
      1.0382,
      1.3124,
      1.5009
    ],
    "triple_inshore": [
      0.8067,
      1.0564,
      1.2319
    ]
  },
  "boat": {
    "builder": "M BOATS",
    "type": "S 40 OD",
    "designer": "SOTO ACEBAL",
    "year": 2008,
    "sizes": {
      "loa": 12.347,
      "beam": 3.8,
      "draft": 2.62,
      "displacement": 4616.0,
      "genoa": 41.04,
      "main": 62.43,
      "spinnaker": 0.0,
      "spinnaker_asym": 189.42,
      "crew": 850.0,
      "wetted_surface": 31.39
    },
    "stability_index": 127.1
  },
  "vpp": {
    "angles": [
      52,
      60,
      75,
      90,
      110,
      120,
      135,
      150
    ],
    "speeds": [
      4,
      6,
      8,
      10,
      12,
      14,
      16,
      20,
      24
    ],
    "52": [
      4.88,
      6.53,
      7.61,
      8.02,
      8.23,
      8.36,
      8.47,
      8.59,
      8.51
    ],
    "60": [
      5.22,
      6.89,
      7.91,
      8.31,
      8.54,
      8.72,
      8.86,
      9.04,
      9.0
    ],
    "75": [
      5.52,
      7.16,
      8.11,
      8.68,
      9.05,
      9.31,
      9.53,
      9.84,
      9.94
    ],
    "90": [
      5.37,
      7.03,
      8.07,
      8.74,
      9.38,
      9.85,
      10.19,
      10.74,
      11.12
    ],
    "110": [
      5.26,
      7.04,
      8.24,
      8.88,
      9.43,
      9.94,
      10.43,
      11.8,
      12.78
    ],
    "120": [
      5.1,
      6.91,
      8.24,
      9.15,
      9.83,
      10.45,
      11.06,
      12.24,
      13.34
    ],
    "135": [
      4.26,
      6.19,
      7.84,
      8.8,
      9.82,
      10.95,
      12.01,
      13.66,
      15.31
    ],
    "150": [
      3.61,
      5.17,
      6.56,
      7.74,
      8.7,
      9.63,
      10.74,
      13.49,
      17.13
    ],
    "beat_angle": [
      42.9,
      42.9,
      40.5,
      39.2,
      38.5,
      38.3,
      38.4,
      38.6,
      40.2
    ],
    "beat_vmg": [
      3.12,
      4.29,
      5.15,
      5.54,
      5.75,
      5.86,
      5.95,
      6.0,
      5.84
    ],
    "run_angle": [
      141.2,
      141.2,
      140.3,
      146.7,
      151.3,
      148.2,
      146.8,
      146.2,
      149.9
    ],
    "run_vmg": [
      3.13,
      4.48,
      5.68,
      6.7,
      7.54,
      8.34,
      9.3,
      11.68,
      14.83
    ]
  }
}