{
  "sailnumber": "FIN/FIN12022",
  "country": "FIN",
  "name": "Caccone",
  "rating": {
    "gph": 627.6,
    "osn": 612.1,
    "triple_offshore": [
      0.8652,
      1.0643,
      1.1741
    ],
    "triple_inshore": [
      0.6806,
      0.8749,
      0.9734
    ]
  },
  "boat": {
    "builder": "J Boats",
    "type": "J/92",
    "designer": "Rod Johnstone",
    "year": 1992,
    "sizes": {
      "loa": 9.15,
      "beam": 3.04,
      "draft": 1.82,
      "displacement": 2700.0,
      "genoa": 26.44,
      "main": 28.47,
      "spinnaker": 0.0,
      "spinnaker_asym": 82.56,
      "crew": 440.0,
      "wetted_surface": 18.74
    },
    "stability_index": -1.0
  },
  "vpp": {
    "angles": [
      52,
      60,
      75,
      90,
      110,
      120,
      135,
      150
    ],
    "speeds": [
      4,
      6,
      8,
      10,
      12,
      14,
      16,
      20,
      24
    ],
    "52": [
      4.15,
      5.47,
      6.29,
      6.63,
      6.75,
      6.82,
      6.87,
      6.93,
      6.93
    ],
    "60": [
      4.42,
      5.72,
      6.45,
      6.77,
      6.91,
      7.0,
      7.06,
      7.15,
      7.17
    ],
    "75": [
      4.58,
      5.87,
      6.55,
      6.9,
      7.14,
      7.27,
      7.38,
      7.54,
      7.62
    ],
    "90": [
      4.43,
      5.8,
      6.62,
      6.99,
      7.23,
      7.49,
      7.68,
      7.94,
      8.14
    ],
    "110": [
      4.4,
      5.82,
      6.73,
      7.21,
      7.58,
      7.88,
      8.16,
      8.7,
      9.14
    ],
    "120": [
      4.27,
      5.7,
      6.66,
      7.2,
      7.67,
      8.1,
      8.53,
      9.56,
      10.9
    ],
    "135": [
      3.74,
      5.17,
      6.26,
      6.89,
      7.41,
      7.93,
      8.52,
      10.66,
      12.88
    ],
    "150": [
      3.1,
      4.38,
      5.48,
      6.34,
      6.88,
      7.31,
      7.75,
      9.03,
      12.5
    ],
    "beat_angle": [
      42.4,
      42.4,
      40.1,
      37.8,
      36.9,
      36.7,
      36.6,
      36.7,
      38.1
    ],
    "beat_vmg": [
      2.65,
      3.63,
      4.35,
      4.74,
      4.88,
      4.95,
      5.0,
      5.03,
      4.95
    ],
    "run_angle": [
      143.8,
      143.8,
      148.2,
      151.2,
      154.3,
      158.5,
      158.2,
      140,
      144.4
    ],
    "run_vmg": [
      2.68,
      3.8,
      4.75,
      5.49,
      6.01,
      6.4,
      6.76,
      7.82,
      10.82
    ]
  }
}