{
  "sailnumber": "POR/ESP6966",
  "country": "POR",
  "name": "WHO'S NEXT",
  "rating": {
    "gph": 571.6,
    "osn": 555.7,
    "triple_offshore": [
      0.9244,
      1.1813,
      1.32
    ],
    "triple_inshore": [
      0.7171,
      0.9616,
      1.0995
    ]
  },
  "boat": {
    "builder": "COMAR",
    "type": "COMET 41S MOD.",
    "designer": "A.VALLICELLI & C.",
    "year": 2000,
    "sizes": {
      "loa": 12.469,
      "beam": 3.93,
      "draft": 2.33,
      "displacement": 6690.0,
      "genoa": 41.66,
      "main": 56.76,
      "spinnaker": 114.13,
      "spinnaker_asym": 99.27,
      "crew": 840.0,
      "wetted_surface": 32.06
    },
    "stability_index": 119.7
  },
  "vpp": {
    "angles": [
      52,
      60,
      75,
      90,
      110,
      120,
      135,
      150
    ],
    "speeds": [
      4,
      6,
      8,
      10,
      12,
      14,
      16,
      20,
      24
    ],
    "52": [
      4.44,
      5.94,
      6.96,
      7.48,
      7.7,
      7.82,
      7.9,
      7.99,
      7.98
    ],
    "60": [
      4.73,
      6.24,
      7.2,
      7.69,
      7.92,
      8.04,
      8.13,
      8.24,
      8.27
    ],
    "75": [
      4.94,
      6.45,
      7.35,
      7.84,
      8.15,
      8.36,
      8.5,
      8.7,
      8.78
    ],
    "90": [
      4.77,
      6.32,
      7.33,
      7.91,
      8.23,
      8.52,
      8.78,
      9.14,
      9.37
    ],
    "110": [
      4.54,
      6.19,
      7.39,
      8.05,
      8.54,
      8.98,
      9.33,
      9.85,
      10.19
    ],
    "120": [
      4.35,
      5.99,
      7.22,
      7.92,
      8.43,
      8.94,
      9.44,
      10.46,
      11.21
    ],
    "135": [
      3.78,
      5.32,
      6.59,
      7.48,
      8.05,
      8.55,
      9.07,
      10.29,
      12.16
    ],
    "150": [
      3.1,
      4.44,
      5.65,
      6.71,
      7.52,
      8.06,
      8.53,
      9.56,
      10.99
    ],
    "beat_angle": [
      42.6,
      42.6,
      40.4,
      38.8,
      37.9,
      38,
      37.8,
      37.9,
      39.3
    ],
    "beat_vmg": [
      2.84,
      3.92,
      4.75,
      5.23,
      5.44,
      5.56,
      5.64,
      5.7,
      5.6
    ],
    "run_angle": [
      141.5,
      141.5,
      147.8,
      151.8,
      157.4,
      164.8,
      170.9,
      173.6,
      163.1
    ],
    "run_vmg": [
      2.68,
      3.85,
      4.9,
      5.82,
      6.61,
      7.26,
      7.78,
      8.66,
      9.65
    ]
  }
}