{
  "sailnumber": "ITA/ITA18079",
  "country": "ITA",
  "name": "VAJRA 4.0",
  "rating": {
    "gph": 639.7,
    "osn": 624.8,
    "triple_offshore": [
      0.8361,
      1.0487,
      1.1726
    ],
    "triple_inshore": [
      0.6478,
      0.8458,
      0.9453
    ]
  },
  "boat": {
    "builder": "Pogo Structures",
    "type": "Pogo 850",
    "designer": "Roland",
    "year": 1999,
    "sizes": {
      "loa": 8.5,
      "beam": 3.64,
      "draft": 1.81,
      "displacement": 3006.0,
      "genoa": 26.13,
      "main": 30.25,
      "spinnaker": 0.0,
      "spinnaker_asym": 76.92,
      "crew": 280.0,
      "wetted_surface": 19.57
    },
    "stability_index": -1.0
  },
  "vpp": {
    "angles": [
      52,
      60,
      75,
      90,
      110,
      120,
      135,
      150
    ],
    "speeds": [
      4,
      6,
      8,
      10,
      12,
      14,
      16,
      20,
      24
    ],
    "52": [
      4.03,
      5.34,
      6.18,
      6.57,
      6.74,
      6.85,
      6.92,
      6.97,
      6.92
    ],
    "60": [
      4.36,
      5.67,
      6.42,
      6.78,
      6.98,
      7.1,
      7.19,
      7.3,
      7.31
    ],
    "75": [
      4.65,
      5.93,
      6.61,
      7.0,
      7.32,
      7.55,
      7.71,
      7.89,
      8.03
    ],
    "90": [
      4.62,
      5.93,
      6.64,
      7.08,
      7.49,
      7.85,
      8.16,
      8.59,
      8.88
    ],
    "110": [
      4.17,
      5.6,
      6.58,
      7.14,
      7.67,
      8.15,
      8.6,
      9.25,
      10.16
    ],
    "120": [
      4.03,
      5.46,
      6.48,
      7.06,
      7.61,
      8.16,
      8.76,
      10.06,
      11.25
    ],
    "135": [
      3.51,
      4.9,
      6.02,
      6.74,
      7.26,
      7.8,
      8.39,
      9.97,
      13.26
    ],
    "150": [
      2.92,
      4.15,
      5.22,
      6.1,
      6.72,
      7.16,
      7.61,
      8.64,
      11.24
    ],
    "beat_angle": [
      44.1,
      44.1,
      42,
      40.2,
      38.6,
      38.4,
      39,
      39.8,
      41.8
    ],
    "beat_vmg": [
      2.55,
      3.47,
      4.15,
      4.53,
      4.74,
      4.83,
      4.87,
      4.84,
      4.69
    ],
    "run_angle": [
      143.9,
      143.9,
      148,
      149.7,
      153.2,
      158.6,
      159.1,
      146.2,
      140.2
    ],
    "run_vmg": [
      2.53,
      3.59,
      4.52,
      5.29,
      5.85,
      6.27,
      6.66,
      7.48,
      9.73
    ]
  }
}