{
  "sailnumber": "LAT/LAT645",
  "country": "LAT",
  "name": "Nicole",
  "rating": {
    "gph": 561.2,
    "osn": 545.5,
    "triple_offshore": [
      0.9474,
      1.2011,
      1.3333
    ],
    "triple_inshore": [
      0.7381,
      0.9793,
      1.0998
    ]
  },
  "boat": {
    "builder": "X-Yachts",
    "type": "X-41",
    "designer": "Jeppesen",
    "year": 2006,
    "sizes": {
      "loa": 12.35,
      "beam": 3.65,
      "draft": 2.33,
      "displacement": 7023.0,
      "genoa": 45.85,
      "main": 52.03,
      "spinnaker": 0.0,
      "spinnaker_asym": 162.83,
      "crew": 830.0,
      "wetted_surface": 33.29
    },
    "stability_index": 131.1
  },
  "vpp": {
    "angles": [
      52,
      60,
      75,
      90,
      110,
      120,
      135,
      150
    ],
    "speeds": [
      4,
      6,
      8,
      10,
      12,
      14,
      16,
      20,
      24
    ],
    "52": [
      4.38,
      5.9,
      6.95,
      7.51,
      7.76,
      7.88,
      7.96,
      8.05,
      8.05
    ],
    "60": [
      4.69,
      6.21,
      7.19,
      7.7,
      7.96,
      8.09,
      8.19,
      8.3,
      8.31
    ],
    "75": [
      4.9,
      6.42,
      7.34,
      7.83,
      8.16,
      8.4,
      8.55,
      8.76,
      8.87
    ],
    "90": [
      4.65,
      6.29,
      7.41,
      7.87,
      8.19,
      8.52,
      8.81,
      9.22,
      9.48
    ],
    "110": [
      4.81,
      6.48,
      7.63,
      8.23,
      8.67,
      8.97,
      9.25,
      9.77,
      10.27
    ],
    "120": [
      4.67,
      6.36,
      7.56,
      8.19,
      8.72,
      9.23,
      9.65,
      10.4,
      11.18
    ],
    "135": [
      4.04,
      5.71,
      7.06,
      7.84,
      8.39,
      8.94,
      9.54,
      11.2,
      13.2
    ],
    "150": [
      3.38,
      4.79,
      6.02,
      7.07,
      7.8,
      8.27,
      8.73,
      9.82,
      12.18
    ],
    "beat_angle": [
      43.1,
      43.1,
      41,
      39.2,
      38.1,
      38,
      37.8,
      37.8,
      38.9
    ],
    "beat_vmg": [
      2.79,
      3.87,
      4.71,
      5.25,
      5.49,
      5.62,
      5.7,
      5.77,
      5.69
    ],
    "run_angle": [
      142.3,
      142.3,
      146,
      149.4,
      153,
      156,
      158.8,
      146.4,
      142.1
    ],
    "run_vmg": [
      2.93,
      4.15,
      5.22,
      6.12,
      6.8,
      7.24,
      7.63,
      8.5,
      10.54
    ]
  }
}