{
  "sailnumber": "KOR/KOR804",
  "country": "KOR",
  "name": "804",
  "rating": {
    "gph": 654.6,
    "osn": 641.4,
    "triple_offshore": [
      0.8229,
      1.0162,
      1.1703
    ],
    "triple_inshore": [
      0.6461,
      0.811,
      0.9392
    ]
  },
  "boat": {
    "builder": "Open Sailing US",
    "type": "POGO 2",
    "designer": "Groupe Finot",
    "year": 2001,
    "sizes": {
      "loa": 6.5,
      "beam": 2.99,
      "draft": 1.58,
      "displacement": 1003.0,
      "genoa": 16.91,
      "main": 24.85,
      "spinnaker": 0.0,
      "spinnaker_asym": 67.53,
      "crew": 230.0,
      "wetted_surface": 12.86
    },
    "stability_index": -1.0
  },
  "vpp": {
    "angles": [
      52,
      60,
      75,
      90,
      110,
      120,
      135,
      150
    ],
    "speeds": [
      4,
      6,
      8,
      10,
      12,
      14,
      16,
      20,
      24
    ],
    "52": [
      4.0,
      5.18,
      5.83,
      6.07,
      6.17,
      6.23,
      6.3,
      6.41,
      6.34
    ],
    "60": [
      4.24,
      5.41,
      6.01,
      6.32,
      6.48,
      6.57,
      6.68,
      6.83,
      6.82
    ],
    "75": [
      4.4,
      5.57,
      6.18,
      6.67,
      7.0,
      7.19,
      7.36,
      7.66,
      7.79
    ],
    "90": [
      4.43,
      5.65,
      6.33,
      6.96,
      7.41,
      7.79,
      8.06,
      8.63,
      9.02
    ],
    "110": [
      4.26,
      5.57,
      6.43,
      7.18,
      7.71,
      8.39,
      9.08,
      10.28,
      11.23
    ],
    "120": [
      4.14,
      5.47,
      6.39,
      7.24,
      8.1,
      8.73,
      9.32,
      11.36,
      12.98
    ],
    "135": [
      3.67,
      5.0,
      6.01,
      6.82,
      7.75,
      8.78,
      10.07,
      12.73,
      14.46
    ],
    "150": [
      3.0,
      4.23,
      5.26,
      6.05,
      6.84,
      7.67,
      8.61,
      12.06,
      15.21
    ],
    "beat_angle": [
      42.3,
      42.3,
      39.9,
      38.8,
      38.6,
      39.8,
      40.2,
      40.8,
      43
    ],
    "beat_vmg": [
      2.58,
      3.45,
      4.01,
      4.22,
      4.29,
      4.31,
      4.33,
      4.34,
      4.19
    ],
    "run_angle": [
      139.8,
      139.8,
      149,
      155.1,
      154.4,
      146.6,
      145.8,
      143,
      148
    ],
    "run_vmg": [
      2.6,
      3.67,
      4.56,
      5.25,
      5.95,
      6.64,
      7.46,
      10.44,
      13.17
    ]
  }
}