{
  "sailnumber": "ESP/ESP3470",
  "country": "ESP",
  "name": "BITXET",
  "rating": {
    "gph": 643.4,
    "osn": 623.2,
    "triple_offshore": [
      0.8127,
      1.0542,
      1.1797
    ],
    "triple_inshore": [
      0.6302,
      0.8616,
      0.9911
    ]
  },
  "boat": {
    "builder": "BENETEAU",
    "type": "First 34.7",
    "designer": "FARR",
    "year": 2005,
    "sizes": {
      "loa": 9.982,
      "beam": 3.37,
      "draft": 2.02,
      "displacement": 4842.0,
      "genoa": 25.01,
      "main": 34.56,
      "spinnaker": 80.36,
      "spinnaker_asym": 72.86,
      "crew": 515.0,
      "wetted_surface": 24.29
    },
    "stability_index": 129.5
  },
  "vpp": {
    "angles": [
      52,
      60,
      75,
      90,
      110,
      120,
      135,
      150
    ],
    "speeds": [
      4,
      6,
      8,
      10,
      12,
      14,
      16,
      20,
      24
    ],
    "52": [
      3.73,
      5.02,
      5.94,
      6.54,
      6.87,
      7.03,
      7.11,
      7.18,
      7.18
    ],
    "60": [
      3.96,
      5.29,
      6.19,
      6.72,
      7.03,
      7.21,
      7.31,
      7.4,
      7.43
    ],
    "75": [
      4.11,
      5.46,
      6.35,
      6.86,
      7.17,
      7.4,
      7.58,
      7.78,
      7.88
    ],
    "90": [
      4.18,
      5.62,
      6.6,
      7.11,
      7.42,
      7.61,
      7.75,
      8.08,
      8.33
    ],
    "110": [
      4.1,
      5.58,
      6.65,
      7.21,
      7.6,
      7.96,
      8.28,
      8.74,
      9.15
    ],
    "120": [
      3.95,
      5.42,
      6.51,
      7.11,
      7.52,
      7.91,
      8.3,
      9.11,
      9.88
    ],
    "135": [
      3.47,
      4.85,
      5.98,
      6.77,
      7.24,
      7.63,
      8.02,
      8.89,
      10.29
    ],
    "150": [
      2.86,
      4.09,
      5.18,
      6.12,
      6.81,
      7.25,
      7.62,
      8.38,
      9.36
    ],
    "beat_angle": [
      43.4,
      43.4,
      41.1,
      39.6,
      38.3,
      37.7,
      37.9,
      38.2,
      39.4
    ],
    "beat_vmg": [
      2.39,
      3.3,
      4.01,
      4.54,
      4.86,
      5.01,
      5.08,
      5.12,
      5.05
    ],
    "run_angle": [
      143.4,
      143.4,
      147.8,
      153.2,
      159.9,
      166.8,
      174.9,
      177.2,
      175.6
    ],
    "run_vmg": [
      2.48,
      3.54,
      4.49,
      5.32,
      6.04,
      6.61,
      7.05,
      7.75,
      8.45
    ]
  }
}