{
  "sailnumber": "ESP/ESP6315",
  "country": "ESP",
  "name": "JERONIMO II",
  "rating": {
    "gph": 573.0,
    "osn": 555.1,
    "triple_offshore": [
      0.8995,
      1.1907,
      1.3394
    ],
    "triple_inshore": [
      0.6915,
      0.9557,
      1.099
    ]
  },
  "boat": {
    "builder": "BENETEAU",
    "type": "FIRST 47.7 (SK)",
    "designer": "B.FARR",
    "year": 1999,
    "sizes": {
      "loa": 14.506,
      "beam": 4.51,
      "draft": 2.28,
      "displacement": 11854.0,
      "genoa": 63.03,
      "main": 59.38,
      "spinnaker": 0.0,
      "spinnaker_asym": 144.48,
      "crew": 725.0,
      "wetted_surface": 43.51
    },
    "stability_index": 117.7
  },
  "vpp": {
    "angles": [
      52,
      60,
      75,
      90,
      110,
      120,
      135,
      150
    ],
    "speeds": [
      4,
      6,
      8,
      10,
      12,
      14,
      16,
      20,
      24
    ],
    "52": [
      4.16,
      5.67,
      6.81,
      7.54,
      7.95,
      8.14,
      8.24,
      8.32,
      8.33
    ],
    "60": [
      4.49,
      6.04,
      7.13,
      7.8,
      8.17,
      8.38,
      8.48,
      8.59,
      8.62
    ],
    "75": [
      4.75,
      6.31,
      7.36,
      7.99,
      8.37,
      8.62,
      8.81,
      9.01,
      9.14
    ],
    "90": [
      4.63,
      6.2,
      7.3,
      8.01,
      8.46,
      8.72,
      8.98,
      9.39,
      9.65
    ],
    "110": [
      4.36,
      6.06,
      7.4,
      8.22,
      8.71,
      9.12,
      9.47,
      9.96,
      10.34
    ],
    "120": [
      4.24,
      5.91,
      7.25,
      8.12,
      8.64,
      9.08,
      9.5,
      10.33,
      10.99
    ],
    "135": [
      3.69,
      5.25,
      6.6,
      7.63,
      8.29,
      8.76,
      9.19,
      10.12,
      11.31
    ],
    "150": [
      3.04,
      4.4,
      5.62,
      6.7,
      7.58,
      8.19,
      8.6,
      9.35,
      10.17
    ],
    "beat_angle": [
      44.6,
      44.6,
      42.6,
      41.1,
      40,
      39.3,
      38.9,
      39,
      39.7
    ],
    "beat_vmg": [
      2.61,
      3.65,
      4.5,
      5.12,
      5.49,
      5.67,
      5.76,
      5.82,
      5.76
    ],
    "run_angle": [
      141.9,
      141.9,
      145.8,
      147.9,
      150.4,
      153.1,
      158.1,
      163.7,
      162.3
    ],
    "run_vmg": [
      2.64,
      3.81,
      4.87,
      5.8,
      6.57,
      7.13,
      7.58,
      8.32,
      8.96
    ]
  }
}