{
  "sailnumber": "ESP/ESP7834",
  "country": "ESP",
  "name": "MON DE L'ONA II",
  "rating": {
    "gph": 615.2,
    "osn": 594.2,
    "triple_offshore": [
      0.8443,
      1.1055,
      1.2404
    ],
    "triple_inshore": [
      0.6578,
      0.9053,
      1.0432
    ]
  },
  "boat": {
    "builder": "QBOATS",
    "type": "VROLIJK 37",
    "designer": "JUDEL/VROLIJK",
    "year": 2003,
    "sizes": {
      "loa": 11.0,
      "beam": 3.25,
      "draft": 2.22,
      "displacement": 5280.0,
      "genoa": 30.88,
      "main": 40.5,
      "spinnaker": 84.69,
      "spinnaker_asym": 0.0,
      "crew": 675.0,
      "wetted_surface": 26.48
    },
    "stability_index": 124.4
  },
  "vpp": {
    "angles": [
      52,
      60,
      75,
      90,
      110,
      120,
      135,
      150
    ],
    "speeds": [
      4,
      6,
      8,
      10,
      12,
      14,
      16,
      20,
      24
    ],
    "52": [
      3.96,
      5.35,
      6.35,
      6.99,
      7.3,
      7.42,
      7.5,
      7.57,
      7.57
    ],
    "60": [
      4.19,
      5.61,
      6.58,
      7.15,
      7.46,
      7.62,
      7.7,
      7.8,
      7.83
    ],
    "75": [
      4.34,
      5.77,
      6.72,
      7.26,
      7.6,
      7.85,
      8.01,
      8.2,
      8.3
    ],
    "90": [
      4.14,
      5.65,
      6.75,
      7.36,
      7.66,
      7.91,
      8.19,
      8.58,
      8.83
    ],
    "110": [
      4.11,
      5.65,
      6.81,
      7.46,
      7.9,
      8.27,
      8.54,
      8.94,
      9.13
    ],
    "120": [
      3.95,
      5.46,
      6.62,
      7.34,
      7.82,
      8.25,
      8.66,
      9.42,
      9.97
    ],
    "135": [
      3.47,
      4.87,
      6.05,
      6.94,
      7.5,
      7.95,
      8.4,
      9.4,
      10.99
    ],
    "150": [
      2.85,
      4.12,
      5.28,
      6.27,
      7.03,
      7.53,
      7.95,
      8.81,
      9.94
    ],
    "beat_angle": [
      42.5,
      42.5,
      40.7,
      39.3,
      37.9,
      37.6,
      37.4,
      37.5,
      38.5
    ],
    "beat_vmg": [
      2.56,
      3.54,
      4.32,
      4.89,
      5.2,
      5.32,
      5.39,
      5.44,
      5.38
    ],
    "run_angle": [
      145.1,
      145.1,
      149.6,
      153,
      158.8,
      165.7,
      171.8,
      176.3,
      171.3
    ],
    "run_vmg": [
      2.47,
      3.57,
      4.57,
      5.45,
      6.21,
      6.83,
      7.32,
      8.1,
      8.9
    ]
  }
}